{
  "_fv": 24,
  "_type": "livingentity",
  "definition": {
    "mobName": "Violet Boarclops",
    "mobLabel": "",
    "mobModelName": "Modelpigclops",
    "mobModelTexture": "violet_boar.png",
    "mobModelGlowTexture": "",
    "modelWidth": 0.6,
    "modelHeight": 1.8,
    "modelShadowSize": 0.5,
    "mountedYOffset": 0.0,
    "hasSpawnEgg": true,
    "spawnEggBaseColor": {
      "value": -26164,
      "falpha": 0.0
    },
    "spawnEggDotColor": {
      "value": -10092442,
      "falpha": 0.0
    },
    "creativeTab": {
      "value": "CUSTOM:GTMMobs"
    },
    "isBoss": true,
    "bossBarColor": "PURPLE",
    "bossBarType": "PROGRESS",
    "equipmentMainHand": {
      "value": ""
    },
    "equipmentOffHand": {
      "value": ""
    },
    "equipmentHelmet": {
      "value": ""
    },
    "equipmentBody": {
      "value": ""
    },
    "equipmentLeggings": {
      "value": ""
    },
    "equipmentBoots": {
      "value": ""
    },
    "mobBehaviourType": "Mob",
    "mobCreatureType": "UNDEFINED",
    "attackStrength": 3,
    "attackKnockback": 2.0,
    "knockbackResistance": 10.0,
    "movementSpeed": 0.6,
    "armorBaseValue": 0.0,
    "trackingRange": 64,
    "health": 300,
    "xpAmount": 10,
    "waterMob": false,
    "flyingMob": false,
    "guiBoundTo": "<NONE>",
    "inventorySize": 9,
    "inventoryStackSize": 64,
    "disableCollisions": false,
    "ridable": false,
    "canControlForward": false,
    "canControlStrafe": false,
    "immuneToFire": true,
    "immuneToArrows": true,
    "immuneToFallDamage": false,
    "immuneToCactus": true,
    "immuneToDrowning": true,
    "immuneToLightning": true,
    "immuneToPotions": true,
    "immuneToPlayer": true,
    "immuneToExplosion": true,
    "immuneToTrident": true,
    "immuneToAnvil": true,
    "immuneToWither": true,
    "immuneToDragonBreath": true,
    "mobDrop": {
      "value": "CUSTOM:VioletRib"
    },
    "livingSound": {
      "value": "entity.zombie_pig.ambient"
    },
    "hurtSound": {
      "value": "entity.zombie_pig.hurt"
    },
    "deathSound": {
      "value": "entity.zombie_pig.death"
    },
    "stepSound": {
      "value": ""
    },
    "spawnParticles": false,
    "particleToSpawn": {
      "value": "CUSTOM:Grimmfire"
    },
    "particleSpawningShape": "Spread",
    "particleSpawningRadious": 0.5,
    "particleAmount": 4,
    "onStruckByLightning": {
      "name": "VioletBoarItIsStruckByLightning"
    },
    "whenMobDies": {
      "name": "VioletBoarEntityDies"
    },
    "whenMobIsHurt": {
      "name": "VioletBoarEntityIsHurt"
    },
    "hasAI": true,
    "aiBase": "(none)",
    "aixml": "<xml xmlns=\"https://developers.google.com/blockly/xml\"><block type=\"aitasks_container\" deletable=\"false\" x=\"50\" y=\"55\"><next><block type=\"attack_entity\"><field name=\"insight\">TRUE</field><field name=\"nearby\">TRUE</field><field name=\"entity\">EntityPlayer</field><field name=\"condition\">null,null</field><next><block type=\"attack_entity\"><field name=\"insight\">TRUE</field><field name=\"nearby\">TRUE</field><field name=\"entity\">EntityPlayerMP</field><field name=\"condition\">null,null</field><next><block type=\"leap_at_target\"><field name=\"speed\">2</field><field name=\"condition\">null,null</field><next><block type=\"attack_on_collide\"><field name=\"speed\">1.2</field><field name=\"longmemory\">TRUE</field><field name=\"condition\">null,null</field><next><block type=\"wander\"><field name=\"speed\">2</field><field name=\"condition\">null,null</field><next><block type=\"attack_action\"><field name=\"callhelp\">TRUE</field><field name=\"condition\">null,null</field><next><block type=\"doors_break\"><field name=\"condition\">null,null</field><next><block type=\"look_around\"><field name=\"condition\">null,null</field><next><block type=\"swim_in_water\"><field name=\"condition\">null,null</field></block></next></block></next></block></next></block></next></block></next></block></next></block></next></block></next></block></next></block></xml>",
    "breedable": false,
    "tameable": false,
    "breedTriggerItems": [],
    "ranged": false,
    "rangedAttackItem": {
      "value": ""
    },
    "rangedItemType": "Default item",
    "spawnThisMob": false,
    "doesDespawnWhenIdle": false,
    "spawningProbability": 20,
    "mobSpawningType": "monster",
    "minNumberOfMobsPerGroup": 4,
    "maxNumberOfMobsPerGroup": 4,
    "restrictionBiomes": [],
    "spawnInDungeons": false
  }
}